clips/__init__.py
clips/_clips.pyd
clips/agenda.py
clips/classes.py
clips/clips_build.py
clips/common.py
clips/environment.py
clips/facts.py
clips/functions.py
clips/modules.py
clips/routers.py
clips/values.py
clipspy-1.0.5.data/data/lib/clips.cdef
clipspy-1.0.5.dist-info/LICENSE.txt
clipspy-1.0.5.dist-info/METADATA
clipspy-1.0.5.dist-info/WHEEL
clipspy-1.0.5.dist-info/top_level.txt
clipspy-1.0.5.dist-info/RECORD
