Metadata-Version: 2.2
Name: clipspy
Version: 1.0.5
Summary: CLIPS Python bindings
Home-page: https://github.com/noxdafox/clipspy
Author: Matteo Cafasso
Author-email: noxdafox@gmail.com
License: BSD
Keywords: clips python cffi expert-system
Classifier: Programming Language :: Python :: 3
Classifier: Programming Language :: Python :: Implementation :: PyPy
Classifier: Development Status :: 5 - Production/Stable
Classifier: Intended Audience :: Developers
Classifier: License :: OSI Approved :: BSD License
License-File: LICENSE.txt
Requires-Dist: cffi>=1.0.0
Dynamic: author
Dynamic: author-email
Dynamic: classifier
Dynamic: description
Dynamic: home-page
Dynamic: keywords
Dynamic: license
Dynamic: requires-dist
Dynamic: summary
